doiExtractor/__init__.py
doiExtractor/doiExtractor.py
doiExtractor/main.py
doiExtractor/openAlex.py
doiExtractor/ExistingPapers/Papers.csv
doiExtractor/ExistingPapers/name_doi_papers.csv
doiExtractor/Outputs/dois.txt
doiExtractor/Outputs/results.csv
doiExtractor/Outputs/results.json
DataExtractorOEG-0.5.2.dist-info/LICENSE.txt
DataExtractorOEG-0.5.2.dist-info/METADATA
DataExtractorOEG-0.5.2.dist-info/WHEEL
DataExtractorOEG-0.5.2.dist-info/entry_points.txt
DataExtractorOEG-0.5.2.dist-info/top_level.txt
DataExtractorOEG-0.5.2.dist-info/RECORD
