Metadata-Version: 2.1
Name: DataExtractorOEG
Version: 0.5.2
Author: Pablo Torija Martínez
License-File: LICENSE.txt
Requires-Dist: beautifulsoup4
Requires-Dist: selenium
Requires-Dist: requests
Requires-Dist: pandas
